[{"date":"1985-12-01","tempmax":14.3,"tempmin":2.1,"temp":7.7,"feelslikemax":14.3,"feelslikemin":2.1,"humidity":60.7,"dew":0.1,"precip":0,"precipcover":0,"windspeed":14.4,"pressure":1026.5,"visibility":7.8,"uvindex":0,"condition":"Partially cloudy"},
{"date":"1985-12-02","tempmax":10.2,"tempmin":1.8,"temp":6.4,"feelslikemax":10.2,"feelslikemin":1.8,"humidity":57.6,"dew":-1.9,"precip":0,"precipcover":0,"windspeed":10.8,"pressure":1029.7,"visibility":5.4,"uvindex":0,"condition":"Clear"},
{"date":"1985-12-03","tempmax":14.2,"tempmin":5.9,"temp":10.5,"feelslikemax":14.2,"feelslikemin":4.4,"humidity":76.5,"dew":6.5,"precip":0,"precipcover":0,"windspeed":25.2,"pressure":1022.4,"visibility":8.2,"uvindex":0,"condition":"Partially cloudy"},
{"date":"1985-12-04","tempmax":15.9,"tempmin":7.1,"temp":11.1,"feelslikemax":15.9,"feelslikemin":7.1,"humidity":71.9,"dew":5.6,"precip":0,"precipcover":0,"windspeed":10.7,"pressure":1022.8,"visibility":5.9,"uvindex":0,"condition":"Partially cloudy"},
{"date":"1985-12-05","tempmax":17.9,"tempmin":3.6,"temp":11,"feelslikemax":17.9,"feelslikemin":3.6,"humidity":85.2,"dew":8.4,"precip":0,"precipcover":0,"windspeed":14.4,"pressure":1022,"visibility":3.2,"uvindex":0,"condition":"Partially cloudy"},
{"date":"1985-12-06","tempmax":12.7,"tempmin":9.1,"temp":10.1,"feelslikemax":12.7,"feelslikemin":6,"humidity":81.6,"dew":7.2,"precip":0,"precipcover":0,"windspeed":25.4,"pressure":1023,"visibility":10.8,"uvindex":0,"condition":"Overcast"},
{"date":"1985-12-07","tempmax":20.1,"tempmin":5.9,"temp":11.1,"feelslikemax":20.1,"feelslikemin":2,"humidity":73.4,"dew":6.4,"precip":0,"precipcover":0,"windspeed":21.6,"pressure":1024.4,"visibility":9.2,"uvindex":0,"condition":"Overcast"},
{"date":"1985-12-08","tempmax":3.7,"tempmin":-1.1,"temp":1.9,"feelslikemax":-0.4,"feelslikemin":-4.9,"humidity":84.2,"dew":-0.6,"precip":0,"precipcover":0,"windspeed":21.8,"pressure":1027.3,"visibility":7.2,"uvindex":0,"condition":"Partially cloudy"},
{"date":"1985-12-09","tempmax":0.8,"tempmin":-2.9,"temp":-0.8,"feelslikemax":-1.7,"feelslikemin":-5.8,"humidity":70.1,"dew":-5.8,"precip":0,"precipcover":0,"windspeed":14.6,"pressure":1028.4,"visibility":10.4,"uvindex":0,"condition":"Partially cloudy"},
{"date":"1985-12-10","tempmax":2,"tempmin":-0.4,"temp":0.7,"feelslikemax":0.6,"feelslikemin":-3.3,"humidity":85.4,"dew":-1.5,"precip":0,"precipcover":0,"windspeed":14.3,"pressure":1027.8,"visibility":4.7,"uvindex":0,"condition":"Overcast"},
{"date":"1985-12-11","tempmax":0.1,"tempmin":-2.8,"temp":-1.2,"feelslikemax":-2.8,"feelslikemin":-7,"humidity":74.5,"dew":-5.3,"precip":0,"precipcover":0,"windspeed":21.8,"pressure":1030.4,"visibility":11.4,"uvindex":0,"condition":"Partially cloudy"},
{"date":"1985-12-12","tempmax":2.4,"tempmin":-3.5,"temp":-1.1,"feelslikemax":-1.2,"feelslikemin":-3.9,"humidity":70.9,"dew":-6,"precip":0,"precipcover":0,"windspeed":14.4,"pressure":1028.9,"visibility":5.2,"uvindex":0,"condition":"Clear"},
{"date":"1985-12-13","tempmax":7.3,"tempmin":-2.8,"temp":1.7,"feelslikemax":7.3,"feelslikemin":-2.8,"humidity":70.3,"dew":-3.5,"precip":0,"precipcover":0,"windspeed":10.8,"pressure":1025.1,"visibility":5.4,"uvindex":0,"condition":"Clear"},
{"date":"1985-12-14","tempmax":6.9,"tempmin":-0.1,"temp":2.8,"feelslikemax":4.1,"feelslikemin":-2.8,"humidity":78.8,"dew":-0.6,"precip":0,"precipcover":0,"windspeed":18,"pressure":1027.4,"visibility":4.5,"uvindex":0,"condition":"Partially cloudy"},
{"date":"1985-12-15","tempmax":3.4,"tempmin":-0.6,"temp":0.8,"feelslikemax":-1.2,"feelslikemin":-5.1,"humidity":62.3,"dew":-6.1,"precip":0,"precipcover":0,"windspeed":21.7,"pressure":1029.4,"visibility":11.2,"uvindex":0,"condition":"Clear"},
{"date":"1985-12-16","tempmax":3.2,"tempmin":-2.3,"temp":0.1,"feelslikemax":0.2,"feelslikemin":-5.8,"humidity":60.7,"dew":-6.9,"precip":0,"precipcover":0,"windspeed":21.7,"pressure":1027.8,"visibility":12.4,"uvindex":0,"condition":"Clear"},
{"date":"1985-12-17","tempmax":5.1,"tempmin":-1.2,"temp":2.6,"feelslikemax":2.7,"feelslikemin":-3.2,"humidity":61.6,"dew":-4.3,"precip":0,"precipcover":0,"windspeed":14.8,"pressure":1028.7,"visibility":8,"uvindex":0,"condition":"Clear"},
{"date":"1985-12-18","tempmax":6.8,"tempmin":-0.8,"temp":3.7,"feelslikemax":5.5,"feelslikemin":-0.8,"humidity":77.1,"dew":0,"precip":0,"precipcover":0,"windspeed":14.3,"pressure":1027.3,"visibility":6.3,"uvindex":0,"condition":"Partially cloudy"},
{"date":"1985-12-19","tempmax":5.7,"tempmin":0.1,"temp":2.6,"feelslikemax":5.7,"feelslikemin":-2.3,"humidity":71.1,"dew":-2.4,"precip":0,"precipcover":0,"windspeed":10.8,"pressure":1032.4,"visibility":7.5,"uvindex":0,"condition":"Clear"},
{"date":"1985-12-20","tempmax":8.1,"tempmin":0.6,"temp":4.7,"feelslikemax":8.1,"feelslikemin":-1.8,"humidity":66.9,"dew":-1.2,"precip":0,"precipcover":0,"windspeed":18,"pressure":1034.7,"visibility":7.4,"uvindex":0,"condition":"Partially cloudy"},
{"date":"1985-12-21","tempmax":10.1,"tempmin":6,"temp":8.2,"feelslikemax":10.1,"feelslikemin":3.1,"humidity":74.9,"dew":4,"precip":0,"precipcover":0,"windspeed":18.4,"pressure":1030.8,"visibility":9.6,"uvindex":0,"condition":"Overcast"},
{"date":"1985-12-22","tempmax":4.7,"tempmin":3.3,"temp":3.7,"feelslikemax":2,"feelslikemin":-0.4,"humidity":92.2,"dew":2.6,"precip":0,"precipcover":0,"windspeed":18.2,"pressure":1031.5,"visibility":3,"uvindex":0,"condition":"Overcast"},
{"date":"1985-12-23","tempmax":5.7,"tempmin":1.2,"temp":3.2,"feelslikemax":2.6,"feelslikemin":-0.3,"humidity":67.3,"dew":-2.5,"precip":0,"precipcover":0,"windspeed":14.7,"pressure":1034,"visibility":6.4,"uvindex":0,"condition":"Partially cloudy"},
{"date":"1985-12-24","tempmax":7.1,"tempmin":-1.9,"temp":2.5,"feelslikemax":5.9,"feelslikemin":-1.9,"humidity":76.9,"dew":-1.3,"precip":0,"precipcover":0,"windspeed":7.2,"pressure":1031.3,"visibility":5.5,"uvindex":0,"condition":"Clear"},
{"date":"1985-12-25","tempmax":7.4,"tempmin":-0.7,"temp":2.7,"feelslikemax":7.4,"feelslikemin":-0.7,"humidity":92.2,"dew":1.5,"precip":0,"precipcover":0,"windspeed":3.6,"pressure":1028.7,"visibility":1.1,"uvindex":0,"condition":"Clear"},
{"date":"1985-12-26","tempmax":9.2,"tempmin":-0.1,"temp":4,"feelslikemax":9.2,"feelslikemin":-2.6,"humidity":92.1,"dew":2.7,"precip":0,"precipcover":0,"windspeed":7.2,"pressure":1026.8,"visibility":0.7,"uvindex":0,"condition":"Partially cloudy"},
{"date":"1985-12-27","tempmax":9.9,"tempmin":3.2,"temp":6.7,"feelslikemax":9.9,"feelslikemin":3.2,"humidity":86.5,"dew":4.5,"precip":0,"precipcover":0,"windspeed":10.8,"pressure":1026.6,"visibility":3.9,"uvindex":0,"condition":"Partially cloudy"},
{"date":"1985-12-28","tempmax":13.2,"tempmin":3.6,"temp":8.5,"feelslikemax":13.2,"feelslikemin":3.6,"humidity":82.1,"dew":5.4,"precip":0,"precipcover":0,"windspeed":14.5,"pressure":1025.4,"visibility":10.6,"uvindex":0,"condition":"Partially cloudy"},
{"date":"1985-12-29","tempmax":18.6,"tempmin":8.3,"temp":12.8,"feelslikemax":18.6,"feelslikemin":8.3,"humidity":79.5,"dew":9.1,"precip":0,"precipcover":0,"windspeed":10.8,"pressure":1018.3,"visibility":6.9,"uvindex":0,"condition":"Partially cloudy"},
{"date":"1985-12-30","tempmax":12.6,"tempmin":4.2,"temp":6.2,"feelslikemax":12.6,"feelslikemin":-0.4,"humidity":86.2,"dew":4.1,"precip":0,"precipcover":0,"windspeed":32.2,"pressure":1020.9,"visibility":4.7,"uvindex":0,"condition":"Overcast"},
{"date":"1985-12-31","tempmax":8.1,"tempmin":2.2,"temp":4.3,"feelslikemax":5.6,"feelslikemin":0,"humidity":63.8,"dew":-2.5,"precip":0,"precipcover":0,"windspeed":18.4,"pressure":1026.6,"visibility":8.4,"uvindex":0,"condition":"Overcast"}]